TraceNinja/__init__.py
TraceNinja/traceninja.py
TraceNinja/modules/__init__.py
TraceNinja/modules/alienvault.py
TraceNinja/modules/crtsh.py
TraceNinja/modules/hackertarget.py
TraceNinja/modules/jldc.py
TraceNinja/modules/rapidapi.py
TraceNinja/modules/securitytrails.py
TraceNinja/utils/__init__.py
TraceNinja/utils/handler.py
TraceNinja/utils/banner/__init__.py
TraceNinja/utils/banner/banner.py
TraceNinja/utils/cli/__init__.py
TraceNinja/utils/cli/cli.py
TraceNinja-1.1.1.dist-info/LICENSE
TraceNinja-1.1.1.dist-info/METADATA
TraceNinja-1.1.1.dist-info/WHEEL
TraceNinja-1.1.1.dist-info/entry_points.txt
TraceNinja-1.1.1.dist-info/top_level.txt
TraceNinja-1.1.1.dist-info/RECORD
