Metadata-Version: 2.1
Name: TraceNinja
Version: 1.1.1
Summary: TraceNinja is a subdomain enumeration tool for Python that allows you to enumerate domains and gather information about them. And much much more on the future ^_^. It's currently under development.
Home-page: https://github.com/mohdh34m/TraceNinja
Author: Mohamed
License: MIT
Classifier: Programming Language :: Python :: 3
Classifier: License :: OSI Approved :: MIT License
Classifier: Operating System :: OS Independent
Requires-Python: >=3.10
License-File: LICENSE
Requires-Dist: packaging==24.1
Requires-Dist: python-dotenv==1.0.1
Requires-Dist: Requests==2.32.3
Requires-Dist: rich==13.8.1
Requires-Dist: setuptools==69.2.0
